<DOMSymbolItem xmlns:xsi="http://www.w3.org/2001/XMLSchema-instance" xmlns="http://ns.adobe.com/xfl/2008/" name="Global/Window - Glossary/glossary elements/glossaryTerm" itemID="4dc2af48-00006cc1" lastModified="1325025649">
  <timeline>
    <DOMTimeline name="glossaryTerm">
      <layers>
        <DOMLayer name="Layer 1" color="#4FFF4F" current="true" isSelected="true">
          <frames>
            <DOMFrame index="0" keyMode="9728">
              <elements>
                <DOMDynamicText name="textbox" width="340" height="26.85" isSelectable="false" renderAsHTML="true" lineType="multiline">
                  <matrix>
                    <Matrix tx="2" ty="2"/>
                  </matrix>
                  <textRuns>
                    <DOMTextRun>
                      <characters>Absolute Humidty</characters>
                      <textAttrs>
                        <DOMTextAttrs aliasText="false" rotation="true" lineSpacing="-1.05" size="22" bitmapSize="440" face="Calibri" fillColor="#0B0B0B"/>
                      </textAttrs>
                    </DOMTextRun>
                  </textRuns>
                </DOMDynamicText>
              </elements>
            </DOMFrame>
          </frames>
        </DOMLayer>
      </layers>
    </DOMTimeline>
  </timeline>
</DOMSymbolItem>