<DOMSymbolItem xmlns:xsi="http://www.w3.org/2001/XMLSchema-instance" xmlns="http://ns.adobe.com/xfl/2008/" name="Custom Content/frame11/frame11_01_content" itemID="4e81dde2-00000b40" linkageExportForAS="true" linkageBaseClass="com.invision.client.movies.Frame11_Content" linkageClassName="frame11_01_content" lastModified="1318961264" lastUniqueIdentifier="7">
  <timeline>
    <DOMTimeline name="frame11_01_content">
      <layers>
        <DOMLayer name="Layer 2" color="#9933CC" current="true" isSelected="true">
          <frames>
            <DOMFrame index="0" keyMode="9728">
              <elements>
                <DOMStaticText width="224" height="38.95" includeOutlines="true" isSelectable="false">
                  <matrix>
                    <Matrix tx="52" ty="401.95"/>
                  </matrix>
                  <textRuns>
                    <DOMTextRun>
                      <characters>ACCOUNT SERVICE&#xD;REPRESENTATIVE</characters>
                      <textAttrs>
                        <DOMTextAttrs alignment="center" aliasText="false" rotation="true" lineSpacing="-0.85" size="18" face="_Gotham Bold*" fillColor="#0B0B0B"/>
                      </textAttrs>
                    </DOMTextRun>
                  </textRuns>
                </DOMStaticText>
                <DOMBitmapInstance libraryItemName="Custom Content/image_graphics/icon_dealerAccounts.png">
                  <matrix>
                    <Matrix a="0.599990844726563" d="0.599990844726563" tx="-52.4" ty="184.55"/>
                  </matrix>
                  <transformationPoint>
                    <Point x="326.5" y="191.5"/>
                  </transformationPoint>
                </DOMBitmapInstance>
                <DOMStaticText width="224" height="38.95" includeOutlines="true" isSelectable="false">
                  <matrix>
                    <Matrix tx="387" ty="401.95"/>
                  </matrix>
                  <textRuns>
                    <DOMTextRun>
                      <characters>NATIONAL ACCOUNT SPECIALIST</characters>
                      <textAttrs>
                        <DOMTextAttrs alignment="center" aliasText="false" rotation="true" lineSpacing="-0.85" size="18" face="_Gotham Bold*" fillColor="#0B0B0B"/>
                      </textAttrs>
                    </DOMTextRun>
                  </textRuns>
                </DOMStaticText>
                <DOMBitmapInstance libraryItemName="Custom Content/image_graphics/icon_csr.png">
                  <matrix>
                    <Matrix a="0.599990844726563" d="0.599990844726563" tx="288.6" ty="173.55"/>
                  </matrix>
                  <transformationPoint>
                    <Point x="326.5" y="191.5"/>
                  </transformationPoint>
                </DOMBitmapInstance>
                <DOMStaticText width="224" height="38.95" includeOutlines="true" isSelectable="false">
                  <matrix>
                    <Matrix tx="732" ty="401.95"/>
                  </matrix>
                  <textRuns>
                    <DOMTextRun>
                      <characters>SALES REPRESENTATIVE </characters>
                      <textAttrs>
                        <DOMTextAttrs alignment="center" aliasText="false" rotation="true" lineSpacing="-0.85" size="18" face="_Gotham Bold*" fillColor="#0B0B0B"/>
                      </textAttrs>
                    </DOMTextRun>
                  </textRuns>
                </DOMStaticText>
                <DOMBitmapInstance libraryItemName="Custom Content/image_graphics/icon_sales.png">
                  <matrix>
                    <Matrix a="0.599990844726563" d="0.599990844726563" tx="625.55" ty="188.55"/>
                  </matrix>
                  <transformationPoint>
                    <Point x="326.5" y="191.5"/>
                  </transformationPoint>
                </DOMBitmapInstance>
                <DOMSymbolInstance libraryItemName="Global/Screen layouts/quiz elements/radio_button" name="radiobutton1_mc" centerPoint3DX="158.65" centerPoint3DY="470.75">
                  <matrix>
                    <Matrix a="0.999740600585938" tx="143.65" ty="455.75"/>
                  </matrix>
                  <transformationPoint>
                    <Point/>
                  </transformationPoint>
                </DOMSymbolInstance>
                <DOMSymbolInstance libraryItemName="Global/Screen layouts/quiz elements/radio_button" name="radiobutton2_mc" centerPoint3DX="500.6" centerPoint3DY="470.75">
                  <matrix>
                    <Matrix a="0.999740600585938" tx="485.6" ty="455.75"/>
                  </matrix>
                  <transformationPoint>
                    <Point/>
                  </transformationPoint>
                </DOMSymbolInstance>
                <DOMSymbolInstance libraryItemName="Global/Screen layouts/quiz elements/radio_button" name="radiobutton3_mc" centerPoint3DX="837.6" centerPoint3DY="470.75">
                  <matrix>
                    <Matrix a="0.999740600585938" tx="822.6" ty="455.75"/>
                  </matrix>
                  <transformationPoint>
                    <Point/>
                  </transformationPoint>
                </DOMSymbolInstance>
              </elements>
            </DOMFrame>
          </frames>
        </DOMLayer>
        <DOMLayer name="txt" color="#4FFF4F" autoNamed="false">
          <frames>
            <DOMFrame index="0" keyMode="9728">
              <elements>
                <DOMStaticText width="860.95" height="44.2" isSelectable="false">
                  <matrix>
                    <Matrix tx="42" ty="42"/>
                  </matrix>
                  <transformationPoint>
                    <Point x="539.75" y="32.05"/>
                  </transformationPoint>
                  <textRuns>
                    <DOMTextRun>
                      <characters>Order Flow Scenario</characters>
                      <textAttrs>
                        <DOMTextAttrs aliasText="false" rotation="true" lineSpacing="-1.95" size="40" face="_Gotham Bold*" fillColor="#2A6786"/>
                      </textAttrs>
                    </DOMTextRun>
                  </textRuns>
                </DOMStaticText>
                <DOMStaticText width="608.95" height="55" isSelectable="false">
                  <matrix>
                    <Matrix tx="42" ty="92"/>
                  </matrix>
                  <textRuns>
                    <DOMTextRun>
                      <characters>Check the box of your job role at New Balance and click the Next button.</characters>
                      <textAttrs>
                        <DOMTextAttrs aliasText="false" rotation="true" size="24" bitmapSize="480" face="_Gotham Bold*" fillColor="#FFFFFF"/>
                      </textAttrs>
                    </DOMTextRun>
                  </textRuns>
                  <filters>
                    <DropShadowFilter angle="90" blurX="3" blurY="3" distance="0" quality="3" strength="0.25"/>
                  </filters>
                </DOMStaticText>
              </elements>
            </DOMFrame>
          </frames>
        </DOMLayer>
      </layers>
    </DOMTimeline>
  </timeline>
</DOMSymbolItem>